Workbook

Sheet Questions
B2: Case BZR Group — Pricing & PM Analyst Jr.
B4: Segue uma extração da base de potenciais clientes (aba DataBase) para que você analise uma operação fictícia de Home Equity (empréstimos com garantia de imóvel). O case simula uma situação real do dia-a-dia da nossa mesa: você acabou de receber uma base de clientes aprovados em análise de crédito e precisa nos dar uma leitura do que está acontecendo.
B6: Sobre os dados
B7: A base contém dados fictícios de clientes que estão buscando um empréstimo com garantia de imóvel e foram aprovados na análise de crédito (credit_approval). A coluna 'closed_at' indica a data de fechamento da operação do empréstimo (quando preenchida).
B9: Regras
B10: • O teste deve ser resolvido utilizando somente os dados presentes neste arquivo.
B11: • Explicite o raciocínio utilizado para chegar às respostas, mantendo cálculos e fórmulas vivas.
B12: • Você pode assumir o que julgar necessário. Quando assumir, deixe explícito.
B13: • Você pode (e deve) criar abas adicionais para responder as questões. Não apague as abas originais.
B14: • Uso de IA: é oportuno usar IA (Claude, ChatGPT, Gemini, Copilot — sua escolha) na resolução do case. Use para análise de dados, geração de visualizações, revisão de texto, o que precisar. Documentar seu uso na aba 'AI_Log' é opcional, mas valorizamos. Importante: na entrevista de defesa do case, vamos te perguntar por que escolheu cada conclusão — então use a IA como copiloto, não como piloto automático.
B16: Questões
B18: Q1. Preencha a área em amarelo da aba 'Q1 - Summary' com os dados da 'DataBase'. Quais conclusões podem ser tiradas?
... B26: Deixe os cálculos e fórmulas utilizados.

Sheet Q1 - Summary
B2: Home Equity
B3: Período | C3: Q3-2024 | D3: Q4-2024 | E3: Q1-2025 | F3: Q2-2025 | G3: Q3-2025 | H3: Q4-2025
B4: Credit Approved ($) | C4: =SUMIFS(DataBase!$I$2:$I$1186,DataBase!$B$2:$B$1186,">="&DATE(2024,7,1),DataBase!$B$2:$B$1186,"<"&DATE(2024,10,1)) -> 9032131 | D4: =SUMIFS(DataBase!$I$2:$I$1186,DataBase!$B$2:$B$1186,">="&DATE(2024,10,1),DataBase!$B$2:$B$1186,"<"&DATE(2025,1,1)) -> 12522505 | E4: =SUMIFS(DataBase!$I$2:$I$1186,DataBase!$B$2:$B$1186,">="&DATE(2025,1,1),DataBase!$B$2:$B$1186,"<"&DATE(2025,4,1)) -> 17756129 | F4: =SUMIFS(DataBase!$I$2:$I$1186,DataBase!$B$2:$B$1186,">="&DATE(2025,4,1),DataBase!$B$2:$B$1186,"<"&DATE(2025,7,1)) -> 29501438 | G4: =SUMIFS(DataBase!$I$2:$I$1186,DataBase!$B$2:$B$1186,">="&DATE(2025,7,1),DataBase!$B$2:$B$1186,"<"&DATE(2025,10,1)) -> 55655676 | H4: =SUMIFS(DataBase!$I$2:$I$1186,DataBase!$B$2:$B$1186,">="&DATE(2025,10,1),DataBase!$B$2:$B$1186,"<"&DATE(2026,1,1)) -> 62921120
B6: property types
B7: house ($) | C7: =SUMIFS(DataBase!$I$2:$I$1186,DataBase!$B$2:$B$1186,">="&DATE(2024,7,1),DataBase!$B$2:$B$1186,"<"&DATE(2024,10,1),DataBase!$O$2:$O$1186,"house") -> 3280131 | D7: =SUMIFS(DataBase!$I$2:$I$1186,DataBase!$B$2:$B$1186,">="&DATE(2024,10,1),DataBase!$B$2:$B$1186,"<"&DATE(2025,1,1),DataBase!$O$2:$O$1186,"house") -> 5427000 | E7: =SUMIFS(DataBase!$I$2:$I$1186,DataBase!$B$2:$B$1186,">="&DATE(2025,1,1),DataBase!$B$2:$B$1186,"<"&DATE(2025,4,1),DataBase!$O$2:$O$1186,"house") -> 7275503 | F7: =SUMIFS(DataBase!$I$2:$I$1186,DataBase!$B$2:$B$1186,">="&DATE(2025,4,1),DataBase!$B$2:$B$1186,"<"&DATE(2025,7,1),DataBase!$O$2:$O$1186,"house") -> 10703166 | G7: =SUMIFS(DataBase!$I$2:$I$1186,DataBase!$B$2:$B$1186,">="&DATE(2025,7,1),DataBase!$B$2:$B$1186,"<"&DATE(2025,10,1),DataBase!$O$2:$O$1186,"house") -> 19581000 | H7: =SUMIFS(DataBase!$I$2:$I$1186,DataBase!$B$2:$B$1186,">="&DATE(2025,10,1),DataBase!$B$2:$B$1186,"<"&DATE(2026,1,1),DataBase!$O$2:$O$1186,"house") -> 24859375
B8: % of credit approved | C8: =IFERROR(C7/C4,0) -> 0.36316247 | D8: =IFERROR(D7/D4,0) -> 0.43337974 | E8: =IFERROR(E7/E4,0) -> 0.40974601 | F8: =IFERROR(F7/F4,0) -> 0.3628015 | G8: =IFERROR(G7/G4,0) -> 0.35182395 | H8: =IFERROR(H7/H4,0) -> 0.39508793
B9: apartment ($) | C9: =SUMIFS(DataBase!$I$2:$I$1186,DataBase!$B$2:$B$1186,">="&DATE(2024,7,1),DataBase!$B$2:$B$1186,"<"&DATE(2024,10,1),DataBase!$O$2:$O$1186,"apartment") -> 4492000 | D9: =SUMIFS(DataBase!$I$2:$I$1186,DataBase!$B$2:$B$1186,">="&DATE(2024,10,1),DataBase!$B$2:$B$1186,"<"&DATE(2025,1,1),DataBase!$O$2:$O$1186,"apartment") -> 6025505 | E9: =SUMIFS(DataBase!$I$2:$I$1186,DataBase!$B$2:$B$1186,">="&DATE(2025,1,1),DataBase!$B$2:$B$1186,"<"&DATE(2025,4,1),DataBase!$O$2:$O$1186,"apartment") -> 8100626 | F9: =SUMIFS(DataBase!$I$2:$I$1186,DataBase!$B$2:$B$1186,">="&DATE(2025,4,1),DataBase!$B$2:$B$1186,"<"&DATE(2025,7,1),DataBase!$O$2:$O$1186,"apartment") -> 15768272 | G9: =SUMIFS(DataBase!$I$2:$I$1186,DataBase!$B$2:$B$1186,">="&DATE(2025,7,1),DataBase!$B$2:$B$1186,"<"&DATE(2025,10,1),DataBase!$O$2:$O$1186,"apartment") -> 32450676 | H9: =SUMIFS(DataBase!$I$2:$I$1186,DataBase!$B$2:$B$1186,">="&DATE(2025,10,1),DataBase!$B$2:$B$1186,"<"&DATE(2026,1,1),DataBase!$O$2:$O$1186,"apartment") -> 34046698
B10: % of credit approved | C10: =IFERROR(C9/C4,0) -> 0.49733557 | D10: =IFERROR(D9/D4,0) -> 0.48117409 | E10: =IFERROR(E9/E4,0) -> 0.45621577 | F10: =IFERROR(F9/F4,0) -> 0.53449164 | G10: =IFERROR(G9/G4,0) -> 0.58306139 | H10: =IFERROR(H9/H4,0) -> 0.54110127
B11: other ($) | C11: =SUMIFS(DataBase!$I$2:$I$1186,DataBase!$B$2:$B$1186,">="&DATE(2024,7,1),DataBase!$B$2:$B$1186,"<"&DATE(2024,10,1),DataBase!$O$2:$O$1186,"other") -> 990000 | D11: =SUMIFS(DataBase!$I$2:$I$1186,DataBase!$B$2:$B$1186,">="&DATE(2024,10,1),DataBase!$B$2:$B$1186,"<"&DATE(2025,1,1),DataBase!$O$2:$O$1186,"other") -> 750000 | E11: =SUMIFS(DataBase!$I$2:$I$1186,DataBase!$B$2:$B$1186,">="&DATE(2025,1,1),DataBase!$B$2:$B$1186,"<"&DATE(2025,4,1),DataBase!$O$2:$O$1186,"other") -> 1780000 | F11: =SUMIFS(DataBase!$I$2:$I$1186,DataBase!$B$2:$B$1186,">="&DATE(2025,4,1),DataBase!$B$2:$B$1186,"<"&DATE(2025,7,1),DataBase!$O$2:$O$1186,"other") -> 2500000 | G11: =SUMIFS(DataBase!$I$2:$I$1186,DataBase!$B$2:$B$1186,">="&DATE(2025,7,1),DataBase!$B$2:$B$1186,"<"&DATE(2025,10,1),DataBase!$O$2:$O$1186,"other") -> 3574000 | H11: =SUMIFS(DataBase!$I$2:$I$1186,DataBase!$B$2:$B$1186,">="&DATE(2025,10,1),DataBase!$B$2:$B$1186,"<"&DATE(2026,1,1),DataBase!$O$2:$O$1186,"other") -> 4015047
B12: % of credit approved | C12: =IFERROR(C11/C4,0) -> 0.10960868 | D12: =IFERROR(D11/D4,0) -> 0.05989217 | E12: =IFERROR(E11/E4,0) -> 0.10024708 | F12: =IFERROR(F11/F4,0) -> 0.084741632 | G12: =IFERROR(G11/G4,0) -> 0.064216271 | H12: =IFERROR(H11/H4,0) -> 0.0638108
B13: NULL (blank information) | C13: =SUMIFS(DataBase!$I$2:$I$1186,DataBase!$B$2:$B$1186,">="&DATE(2024,7,1),DataBase!$B$2:$B$1186,"<"&DATE(2024,10,1),DataBase!$O$2:$O$1186,"NULL") -> 270000 | D13: =SUMIFS(DataBase!$I$2:$I$1186,DataBase!$B$2:$B$1186,">="&DATE(2024,10,1),DataBase!$B$2:$B$1186,"<"&DATE(2025,1,1),DataBase!$O$2:$O$1186,"NULL") -> 320000 | E13: =SUMIFS(DataBase!$I$2:$I$1186,DataBase!$B$2:$B$1186,">="&DATE(2025,1,1),DataBase!$B$2:$B$1186,"<"&DATE(2025,4,1),DataBase!$O$2:$O$1186,"NULL") -> 600000 | F13: =SUMIFS(DataBase!$I$2:$I$1186,DataBase!$B$2:$B$1186,">="&DATE(2025,4,1),DataBase!$B$2:$B$1186,"<"&DATE(2025,7,1),DataBase!$O$2:$O$1186,"NULL") -> 530000 | G13: =SUMIFS(DataBase!$I$2:$I$1186,DataBase!$B$2:$B$1186,">="&DATE(2025,7,1),DataBase!$B$2:$B$1186,"<"&DATE(2025,10,1),DataBase!$O$2:$O$1186,"NULL") -> 50000 | H13: =SUMIFS(DataBase!$I$2:$I$1186,DataBase!$B$2:$B$1186,">="&DATE(2025,10,1),DataBase!$B$2:$B$1186,"<"&DATE(2026,1,1),DataBase!$O$2:$O$1186,"NULL") -> 0
B14: % of credit approved | C14: =IFERROR(C13/C4,0) -> 0.029893278 | D14: =IFERROR(D13/D4,0) -> 0.025553993 | E14: =IFERROR(E13/E4,0) -> 0.033791149 | F14: =IFERROR(F13/F4,0) -> 0.017965226 | G14: =IFERROR(G13/G4,0) -> 0.00089838097 | H14: =IFERROR(H13/H4,0) -> 0
B16: Closed operations ($) | C16: =SUMIFS(DataBase!$I$2:$I$1186,DataBase!$B$2:$B$1186,">="&DATE(2024,7,1),DataBase!$B$2:$B$1186,"<"&DATE(2024,10,1),DataBase!$P$2:$P$1186,1) -> 5715131 | D16: =SUMIFS(DataBase!$I$2:$I$1186,DataBase!$B$2:$B$1186,">="&DATE(2024,10,1),DataBase!$B$2:$B$1186,"<"&DATE(2025,1,1),DataBase!$P$2:$P$1186,1) -> 5773000 | E16: =SUMIFS(DataBase!$I$2:$I$1186,DataBase!$B$2:$B$1186,">="&DATE(2025,1,1),DataBase!$B$2:$B$1186,"<"&DATE(2025,4,1),DataBase!$P$2:$P$1186,1) -> 8399000 | F16: =SUMIFS(DataBase!$I$2:$I$1186,DataBase!$B$2:$B$1186,">="&DATE(2025,4,1),DataBase!$B$2:$B$1186,"<"&DATE(2025,7,1),DataBase!$P$2:$P$1186,1) -> 12174000 | G16: =SUMIFS(DataBase!$I$2:$I$1186,DataBase!$B$2:$B$1186,">="&DATE(2025,7,1),DataBase!$B$2:$B$1186,"<"&DATE(2025,10,1),DataBase!$P$2:$P$1186,1) -> 11259000 | H16: =SUMIFS(DataBase!$I$2:$I$1186,DataBase!$B$2:$B$1186,">="&DATE(2025,10,1),DataBase!$B$2:$B$1186,"<"&DATE(2026,1,1),DataBase!$P$2:$P$1186,1) -> 13487201
B17: % (closed / credit approved) | C17: =IFERROR(C16/C4,0) -> 0.63275555 | D17: =IFERROR(D16/D4,0) -> 0.46101 | E17: =IFERROR(E16/E4,0) -> 0.47301977 | F17: =IFERROR(F16/F4,0) -> 0.41265785 | G17: =IFERROR(G16/G4,0) -> 0.20229743 | H17: =IFERROR(H16/H4,0) -> 0.21435094
B18: Legenda (linha % fechado/aprovado): | C18: favorável (maior %) | D18: → | E18: atenção (menor %)
B20: Análises e Conclusões
B21: Crescimento consistente do credito aprovado a cada trimestre (R$ 9,0M em Q3-24 ate R$ 62,9M em Q4-25, alta de ~7x em 6 trimestres), puxado majoritariamente por apartamentos (45-58% do volume) e casas (35-43%); 'outros' (comercial/terreno) e registros sem tipo informado sao marginais e o 'sem tipo' vem caindo (de 3,0% para 0% do volume, sinal de cadastro melhorando). A % fechado/aprovado cai de 63% (Q3-24) para ~20-21% (Q3/Q4-25): parte e efeito natural de safra (operacoes recentes ainda nao tiveram tempo de fechar - mediana de 56 dias entre aprovacao e fechamento), mas a queda persiste mesmo em Q3-2025, que ja teve 6+ meses de maturacao ate o corte dos dados (mar/2026) - isso sugere tambem uma desaceleracao real no funil de fechamento, nao so efeito de safra. Ha tambem uma limitacao de qualidade de dado que afeta a leitura de 'fechado': closed_at esta em branco em ~68% das linhas e 11 registros tem closed_at anterior a credit_approval (tratados aqui como nao fechados). Ver aba 'Q4 - Qualidade de Dados' para detalhe.

Sheet Q2 - Canal
B1: Aquisição por Canal
B2: Canal | C2: Nº de operações | D2: Volume aprovado (R$) | E2: % do volume total | F2: Conversão (qtd fechada/qtd) | G2: Conversão (R$ fechado/R$ aprovado)
B3: organic | C3: =COUNTIFS(DataBase!$M$2:$M$1186,"organic") -> 760 | D3: =SUMIFS(DataBase!$I$2:$I$1186,DataBase!$M$2:$M$1186,"organic") -> 126093825 | E3: =D3/SUM($D$3:$D$8) -> 0.63177887 | F3: =COUNTIFS(DataBase!$M$2:$M$1186,"organic",DataBase!$P$2:$P$1186,1)/C3 -> 0.30921053 | G3: =SUMIFS(DataBase!$I$2:$I$1186,DataBase!$M$2:$M$1186,"organic",DataBase!$P$2:$P$1186,1)/D3 -> 0.28113611
B4: offline | C4: =COUNTIFS(DataBase!$M$2:$M$1186,"offline") -> 140 | D4: =SUMIFS(DataBase!$I$2:$I$1186,DataBase!$M$2:$M$1186,"offline") -> 34679289 | E4: =D4/SUM($D$3:$D$8) -> 0.17375666 | F4: =COUNTIFS(DataBase!$M$2:$M$1186,"offline",DataBase!$P$2:$P$1186,1)/C4 -> 0.27857143 | G4: =SUMIFS(DataBase!$I$2:$I$1186,DataBase!$M$2:$M$1186,"offline",DataBase!$P$2:$P$1186,1)/D4 -> 0.26975755
B5: social_media | C5: =COUNTIFS(DataBase!$M$2:$M$1186,"social_media") -> 137 | D5: =SUMIFS(DataBase!$I$2:$I$1186,DataBase!$M$2:$M$1186,"social_media") -> 17625014 | E5: =D5/SUM($D$3:$D$8) -> 0.088308142 | F5: =COUNTIFS(DataBase!$M$2:$M$1186,"social_media",DataBase!$P$2:$P$1186,1)/C5 -> 0.29927007 | G5: =SUMIFS(DataBase!$I$2:$I$1186,DataBase!$M$2:$M$1186,"social_media",DataBase!$P$2:$P$1186,1)/D5 -> 0.39220814
B6: other | C6: =COUNTIFS(DataBase!$M$2:$M$1186,"other") -> 69 | D6: =SUMIFS(DataBase!$I$2:$I$1186,DataBase!$M$2:$M$1186,"other") -> 10822251 | E6: =D6/SUM($D$3:$D$8) -> 0.054223666 | F6: =COUNTIFS(DataBase!$M$2:$M$1186,"other",DataBase!$P$2:$P$1186,1)/C6 -> 0.4057971 | G6: =SUMIFS(DataBase!$I$2:$I$1186,DataBase!$M$2:$M$1186,"other",DataBase!$P$2:$P$1186,1)/D6 -> 0.4578651
B7: affiliates | C7: =COUNTIFS(DataBase!$M$2:$M$1186,"affiliates") -> 51 | D7: =SUMIFS(DataBase!$I$2:$I$1186,DataBase!$M$2:$M$1186,"affiliates") -> 6945000 | E7: =D7/SUM($D$3:$D$8) -> 0.034797138 | F7: =COUNTIFS(DataBase!$M$2:$M$1186,"affiliates",DataBase!$P$2:$P$1186,1)/C7 -> 0.33333333 | G7: =SUMIFS(DataBase!$I$2:$I$1186,DataBase!$M$2:$M$1186,"affiliates",DataBase!$P$2:$P$1186,1)/D7 -> 0.26205904
B8: remarketing | C8: =COUNTIFS(DataBase!$M$2:$M$1186,"remarketing") -> 26 | D8: =SUMIFS(DataBase!$I$2:$I$1186,DataBase!$M$2:$M$1186,"remarketing") -> 3420000 | E8: =D8/SUM($D$3:$D$8) -> 0.017135524 | F8: =COUNTIFS(DataBase!$M$2:$M$1186,"remarketing",DataBase!$P$2:$P$1186,1)/C8 -> 0.26923077 | G8: =SUMIFS(DataBase!$I$2:$I$1186,DataBase!$M$2:$M$1186,"remarketing",DataBase!$P$2:$P$1186,1)/D8 -> 0.24707602
B9: (sem canal informado) | C9: =COUNTBLANK(DataBase!$M$2:$M$1186) -> 2 | D9: =SUMIFS(DataBase!$I$2:$I$1186,DataBase!$M$2:$M$1186,"") -> 0 | E9: =IFERROR(D9/SUM($D$3:$D$8),0) -> 0 | F9: =IFERROR(COUNTIFS(DataBase!$M$2:$M$1186,"",DataBase!$P$2:$P$1186,1)/C9,0) -> 0 | G9: =IFERROR(SUMIFS(DataBase!$I$2:$I$1186,DataBase!$M$2:$M$1186,"",DataBase!$P$2:$P$1186,1)/D9,0) -> 0
B10: Legenda (colunas Conversão): | C10: favorável (maior conversão) | D10: → | E10: atenção (menor conversão) | F10: → | G10: não comparável (amostra insuficiente: 2 registros)
B12: Leitura e recomendacao
B13: Volume: 'organic' e disparado o canal mais relevante (760 operacoes, R$ 126,1M, ~64% do numero de operacoes da base). Conversao por quantidade: 'other' (40,6%) e 'affiliates' (33,3%) convertem melhor que organic (30,9%); por R$ convertido, 'other' (45,8%) e 'social_media' (39,2%) se destacam - ou seja, quando convertem, trazem tickets maiores. 'remarketing' e o mais fraco nos dois criterios e tem o menor volume (26 operacoes). Como Strategic Planner buscando crescer rapido, eu NAO cortaria organic (e a base de volume e conversao solida, provavelmente custo de aquisicao baixo por ser organico) - manteria como piso de operacao e reforcaria SEO/conteudo/indicacao que alimentam esse canal. Direcionaria o incremental de budget pago para 'social_media' (bom volume - 137 operacoes - e melhor conversao em R$) e testaria aumento controlado em 'affiliates' e 'other', pois convertem melhor mas tem amostra pequena (69 e 51 operacoes) - antes de alocar peso alto, rodaria um teste A/B maior para confirmar se a conversao se mantem em escala. Reduziria/pausaria 'remarketing' dado o pior resultado combinado a baixo volume, redirecionando essa verba para o teste em social_media/other. Isso e uma leitura sobre uma amostra de ate 1185 operacoes - o ideal e sempre cruzar com CAC real por canal (nao disponivel nesta base) antes de mudar orcamento de verdade.

Sheet Q3
B1: Mapeamento do Processo Operacional
B3: 1. Aprovacao de credito | C3: → | D3: 2. Due diligence do imovel | E3: → | F3: 3. Formalizacao e assinatura | G3: → | H3: 4. Liberacao de recursos
B4: Analise de credito aprova o cliente (credit_approval). Cadastro do imovel dado em garantia e registrado. | D4: Avaliacao do imovel (laudo de garantia), checagem de matricula/onus e documentacao do cliente. | F4: Elaboracao do contrato, assinatura das partes e registro do gravame/garantia em cartorio. | H4: Liberacao/transferencia do valor ao cliente (closed_at) apos confirmacao do registro.
B6: Indicadores de controle da operacao
B7: Lead time medio aprovacao -> fechamento (dias) | D7: =SUMPRODUCT(DataBase!$P$2:$P$1186*(DataBase!$C$2:$C$1186-DataBase!$B$2:$B$1186))/SUM(DataBase!$P$2:$P$1186) -> 63.93188
B8: Lead time mediano (dias) | D8: {=MEDIAN(IF(DataBase!$P$2:$P$1186=1,DataBase!$C$2:$C$1186-DataBase!$B$2:$B$1186))} -> 56
B9: Taxa de conversao aprovacao -> fechamento (%) | D9: =SUM(DataBase!$P$2:$P$1186)/COUNTA(DataBase!$A$2:$A$1186) -> 0.30970464
B10: Operacoes aprovadas ainda nao fechadas (pipeline aberto) | D10: =COUNTA(DataBase!$A$2:$A$1186)-SUM(DataBase!$P$2:$P$1186) -> 818
B11: % de fechamentos com data inconsistente (closed_at < aprovacao) | D11: =COUNTIFS(DataBase!$C$2:$C$1186,"<>",DataBase!$P$2:$P$1186,0)/COUNTIF(DataBase!$C$2:$C$1186,"<>") -> 0.029100529
B13: Sugestão
B14: Sugestão adicional — métricas não calculáveis só com esta base, mas que seriam o próximo passo natural para investigar a queda de conversão e o pipeline de 818 operações em aberto identificados nesta análise: 1) SLA por etapa do funil (dias entre aprovação → avaliação do imóvel → assinatura/registro do contrato → liberação de recursos). Hoje só medimos o tempo total aprovação→fechamento (mediana de 56 dias); sem o tempo de cada etapa isolada, não é possível saber ONDE o funil está travando — se é na due diligence do imóvel, na formalização em cartório ou na liberação do valor. 2) Taxa de desistência/cancelamento pós-aprovação (% de operações que saem do funil sem fechar por decisão do cliente, reprovação em due diligence ou desistência da instituição), separada do simples 'ainda não fechou'. Isso ajudaria a distinguir se a queda no % fechado/aprovado (de 63% em Q3-24 para ~20-21% em Q3/Q4-25) é efeito natural de safra, cancelamento real, ou uma mistura dos dois. 3) Aging do pipeline aberto — distribuição de quanto tempo cada uma das 818 operações pendentes já está parada, não só a mediana histórica de quem já fechou. Um pipeline com muitas operações há mais de 90-120 dias sem movimento é um sinal de alerta operacional bem diferente de um pipeline jovem que simplesmente ainda não teve tempo de fechar.

Sheet Q4 - Qualidade de Dados
B1: Qualidade de Dados — Achados e Tratamento
B2: Problema encontrado | C2: Quantidade (formula ao vivo) | D2: Como foi tratado nesta analise
B3: Grafia/idioma inconsistente em property_type (ex.: 'Apartment', 'APARTMENT', 'apto', 'Apartamento', 'casa', 'Casa' misturados com o padrao em ingles) | C3: =SUMPRODUCT((DataBase!$J$2:$J$1186<>"")*(1-(EXACT(DataBase!$J$2:$J$1186,"apartment")+EXACT(DataBase!$J$2:$J$1186,"house")+EXACT(DataBase!$J$2:$J$1186,"commercial")+EXACT(DataBase!$J$2:$J$1186,"land")))) -> 17 | D3: Criada coluna auxiliar DataBase!O (property_type_norm) com VLOOKUP em aba Lookup_PropertyType, normalizando tudo para apartment/house/other.
B4: closed_at anterior a credit_approval (fechamento antes da aprovacao - logicamente impossivel) | C4: =COUNTIFS(DataBase!$C$2:$C$1186,"<>",DataBase!$P$2:$P$1186,0) -> 11 | D4: Criada coluna auxiliar DataBase!P (is_closed_valid); esses registros sao tratados como 'nao fechado' em todos os calculos (Q1, Q2, Q3), nunca descartados da base.
B5: customer_age menor que 18 anos (juridicamente invalido para contrato de credito) | C5: =COUNTIF(DataBase!$K$2:$K$1186,"<18") -> 1 | D5: Mantido na base (nao exclui linha), mas sinalizado como erro provavel de digitacao (ex.: 9 em vez de 39/91); nao afeta os KPIs de Q1/Q2/Q3 pois nenhum deles agrega por idade.
B6: Registros com credit_approval fora da janela pedida no template (Q3-2024 a Q4-2025): 3 anteriores a jul/2024 e 59 em 2026 (ate 28/mar/2026) | C6: =COUNTIFS(DataBase!$B$2:$B$1186,"<"&DATE(2024,7,1))+COUNTIFS(DataBase!$B$2:$B$1186,">="&DATE(2026,1,1)) -> 62 | D6: Nao somados nas colunas de Q1 - Summary (que cobre so as 6 colunas do template); contados a parte aqui para nao sumir da leitura geral.
B7: loan_amount maior que property_value (LTV acima de 100% - risco atipico p/ credito com garantia real) | C7: =SUMPRODUCT((DataBase!$I$2:$I$1186>DataBase!$H$2:$H$1186)*1) -> 18 | D7: Nao alterado (pode ser legitimo - refinanciamento, avaliacao desatualizada do imovel etc.); sinalizado para revisao de underwriting, nao e um erro de digitacao obvio.
B8: Alta proporcao de nulos em loan_term (41,0%) e credit_score (41,4%) - quase as mesmas 486 linhas | C8: =COUNTBLANK(DataBase!$F$2:$F$1186) -> 486 | D8: Tratado como categoria 'nao informado' nas quebras, nunca removendo a linha; hipotese registrada: pode ser etapa do funil ainda nao concluida (pre-aprovacao sem underwriting completo) - vale confirmar com o time de originacao.
B9: state em branco (1,6% das linhas) | C9: =COUNTBLANK(DataBase!$D$2:$D$1186) -> 19 | D9: Mantido como 'nao informado'; nao afeta os KPIs pedidos (Q1/Q2/Q3 nao segmentam por estado).
B11: Todos os numeros acima sao formulas vivas que leem direto da aba DataBase (incluindo as colunas auxiliares O e P). Ver dados/interim/anomalias.csv para a lista de ids afetados por cada problema (so id + tipo de problema, sem nenhuma outra coluna).

Sheet Cálculos
B2: Memória de Cálculo — Conferência com o Dashboard
B3: Cada linha abaixo é uma fórmula viva desta pasta de trabalho (referencia as abas 'Q1 - Summary', 'Q2 - Canal', 'Q3', 'Q4 - Qualidade de Dados' e 'DataBase' — nenhum valor é digitado à mão). A coluna 'Valor no dashboard' é o snapshot publicado em dashboard/public/data/dashboard_data.json; a coluna 'Bate?' confirma, célula a célula, que o Excel e o dashboard chegam ao mesmo número.
B4: Fonte: Case_Fintech_2026.xlsx (hash b34cf30b4933422c) · 1185 linhas na base, 1123 na janela Q3-2024 a Q4-2025 · dashboard gerado em 2026-09-22 22:27:10.
B6: Métrica | C6: Onde aparece no dashboard | D6: Fórmula usada (texto) | E6: Valor no Excel (ao vivo) | F6: Valor no dashboard | G6: Precisão (casas decimais) | H6: Bate?
B7: Total aprovado no período (R$) | C7: Visão Geral — card "Crédito aprovado" | D7: =_xlfn.FORMULATEXT(E7) -> =SOMA('Q1 - Summary'!C4:H4) | E7: =SUM('Q1 - Summary'!C4:H4) -> 187388999 | F7: 187388999 | G7: 0 | H7: =IF(ROUND(E7,G7)=ROUND(F7,G7),"OK","DIVERGE") -> OK
B8: Total fechado no período (R$) | C8: Visão Geral — card "Fechado" | D8: =_xlfn.FORMULATEXT(E8) -> =SOMA('Q1 - Summary'!C16:H16) | E8: =SUM('Q1 - Summary'!C16:H16) -> 56807332 | F8: 56807332 | G8: 0 | H8: =IF(ROUND(E8,G8)=ROUND(F8,G8),"OK","DIVERGE") -> OK
B9: % fechado sobre aprovado (período) | C9: Visão Geral — card "Fechado" | D9: =_xlfn.FORMULATEXT(E9) -> =E8/E7 | E9: =E8/E7 -> 0.3031519 | F9: 0.3032 | G9: 4 | H9: =IF(ROUND(E9,G9)=ROUND(F9,G9),"OK","DIVERGE") -> OK
B10: Nº de operações na janela (Q3-24 a Q4-25) | C10: Visão Geral — base do dashboard | D10: =_xlfn.FORMULATEXT(E10) -> =CONTAR.SE.S(DataBase!$B$2:$B$1186;">="&DATA(2024;7;1);DataBase!$B$2:$B$1186;"<"&DATA(2026;1;1)) | E10: =COUNTIFS(DataBase!$B$2:$B$1186,">="&DATE(2024,7,1),DataBase!$B$2:$B$1186,"<"&DATE(2026,1,1)) -> 1123 | F10: 1123 | G10: 0 | H10: =IF(ROUND(E10,G10)=ROUND(F10,G10),"OK","DIVERGE") -> OK
B11: Lead time médio, aprovação → fechamento (dias) | C11: Visão Geral / Operação | D11: =_xlfn.FORMULATEXT(E11) -> ='Q3'!D7 | E11: ='Q3'!D7 -> 63.93188 | F11: 63.9 | G11: 1 | H11: =IF(ROUND(E11,G11)=ROUND(F11,G11),"OK","DIVERGE") -> OK
B12: Lead time mediano (dias) | C12: Operação | D12: =_xlfn.FORMULATEXT(E12) -> ='Q3'!D8 | E12: ='Q3'!D8 -> 56 | F12: 56 | G12: 1 | H12: =IF(ROUND(E12,G12)=ROUND(F12,G12),"OK","DIVERGE") -> OK
B13: Pipeline aberto (aprovadas, ainda não fechadas) | C13: Visão Geral — card "Pipeline aberto" / Operação | D13: =_xlfn.FORMULATEXT(E13) -> ='Q3'!D10 | E13: ='Q3'!D10 -> 818 | F13: 818 | G13: 0 | H13: =IF(ROUND(E13,G13)=ROUND(F13,G13),"OK","DIVERGE") -> OK
B14: Taxa de conversão geral, aprovação → fechamento (%) | C14: Operação | D14: =_xlfn.FORMULATEXT(E14) -> ='Q3'!D9 | E14: ='Q3'!D9 -> 0.30970464 | F14: 0.3097 | G14: 4 | H14: =IF(ROUND(E14,G14)=ROUND(F14,G14),"OK","DIVERGE") -> OK
B15: Volume aprovado — Orgânico (R$) | C15: Canais | D15: =_xlfn.FORMULATEXT(E15) -> ='Q2 - Canal'!D3 | E15: ='Q2 - Canal'!D3 -> 126093825 | F15: 126093825 | G15: 0 | H15: =IF(ROUND(E15,G15)=ROUND(F15,G15),"OK","DIVERGE") -> OK
B16: Nº de operações — Orgânico | C16: Canais | D16: =_xlfn.FORMULATEXT(E16) -> ='Q2 - Canal'!C3 | E16: ='Q2 - Canal'!C3 -> 760 | F16: 760 | G16: 0 | H16: =IF(ROUND(E16,G16)=ROUND(F16,G16),"OK","DIVERGE") -> OK
B17: Conversão por valor — Orgânico (%) | C17: Canais | D17: =_xlfn.FORMULATEXT(E17) -> ='Q2 - Canal'!G3 | E17: ='Q2 - Canal'!G3 -> 0.28113611 | F17: 0.2811 | G17: 4 | H17: =IF(ROUND(E17,G17)=ROUND(F17,G17),"OK","DIVERGE") -> OK
B18: Volume aprovado — Redes sociais (R$) | C18: Canais | D18: =_xlfn.FORMULATEXT(E18) -> ='Q2 - Canal'!D5 | E18: ='Q2 - Canal'!D5 -> 17625014 | F18: 17625014 | G18: 0 | H18: =IF(ROUND(E18,G18)=ROUND(F18,G18),"OK","DIVERGE") -> OK
B19: Conversão por valor — Redes sociais (%) | C19: Canais | D19: =_xlfn.FORMULATEXT(E19) -> ='Q2 - Canal'!G5 | E19: ='Q2 - Canal'!G5 -> 0.39220814 | F19: 0.3922 | G19: 4 | H19: =IF(ROUND(E19,G19)=ROUND(F19,G19),"OK","DIVERGE") -> OK
B20: Volume aprovado — Outro (R$) | C20: Canais | D20: =_xlfn.FORMULATEXT(E20) -> ='Q2 - Canal'!D6 | E20: ='Q2 - Canal'!D6 -> 10822251 | F20: 10822251 | G20: 0 | H20: =IF(ROUND(E20,G20)=ROUND(F20,G20),"OK","DIVERGE") -> OK
B21: Conversão por quantidade — Outro (%) | C21: Canais | D21: =_xlfn.FORMULATEXT(E21) -> ='Q2 - Canal'!F6 | E21: ='Q2 - Canal'!F6 -> 0.4057971 | F21: 0.4058 | G21: 4 | H21: =IF(ROUND(E21,G21)=ROUND(F21,G21),"OK","DIVERGE") -> OK
B22: Nº de operações — Não informado (sem canal preenchido) | C22: Canais — legenda "Não informado" | D22: =_xlfn.FORMULATEXT(E22) -> ='Q2 - Canal'!C9 | E22: ='Q2 - Canal'!C9 -> 2 | F22: 2 | G22: 0 | H22: =IF(ROUND(E22,G22)=ROUND(F22,G22),"OK","DIVERGE") -> OK
B23: Tipos de problema encontrados na base | C23: Qualidade de Dados — card "Tipos de problema" | D23: =_xlfn.FORMULATEXT(E23) -> =CONTAR.VAL('Q4 - Qualidade de Dados'!B3:B9) | E23: =COUNTA('Q4 - Qualidade de Dados'!B3:B9) -> 7 | F23: 7 | G23: 0 | H23: =IF(ROUND(E23,G23)=ROUND(F23,G23),"OK","DIVERGE") -> OK
B24: Ocorrências sinalizadas no total (com possível sobreposição) | C24: Qualidade de Dados — card "Ocorrências sinalizadas" | D24: =_xlfn.FORMULATEXT(E24) -> =SOMA('Q4 - Qualidade de Dados'!C3:C9) | E24: =SUM('Q4 - Qualidade de Dados'!C3:C9) -> 614 | F24: 614 | G24: 0 | H24: =IF(ROUND(E24,G24)=ROUND(F24,G24),"OK","DIVERGE") -> OK
B25: Problemas críticos (closed_at inválido + idade < 18) | C25: Qualidade de Dados — card "Problemas críticos" | D25: =_xlfn.FORMULATEXT(E25) -> ='Q4 - Qualidade de Dados'!C4+'Q4 - Qualidade de Dados'!C5 | E25: ='Q4 - Qualidade de Dados'!C4+'Q4 - Qualidade de Dados'!C5 -> 12 | F25: 12 | G25: 0 | H25: =IF(ROUND(E25,G25)=ROUND(F25,G25),"OK","DIVERGE") -> OK
B26: Linhas excluídas da base | C26: Qualidade de Dados — card "Linhas excluídas da base" | D26: Nenhuma linha é removida em nenhum cálculo (Q1/Q2/Q3) — todos os problemas da aba "Q4" são tratados, nunca excluídos. | E26: 0 | F26: 0 | G26: 0 | H26: =IF(ROUND(E26,G26)=ROUND(F26,G26),"OK","DIVERGE") -> OK
B27: % fechado — Q3-2024 (primeiro ponto do gráfico de linha) | C27: Visão Geral — gráfico "Fechado vs aprovado por trimestre" | D27: =_xlfn.FORMULATEXT(E27) -> ='Q1 - Summary'!C17 | E27: ='Q1 - Summary'!C17 -> 0.63275555 | F27: 0.6328 | G27: 4 | H27: =IF(ROUND(E27,G27)=ROUND(F27,G27),"OK","DIVERGE") -> OK
B28: % fechado — Q2-2025 (início da zona "queda atípica") | C28: idem — zona sombreada do gráfico | D28: =_xlfn.FORMULATEXT(E28) -> ='Q1 - Summary'!F17 | E28: ='Q1 - Summary'!F17 -> 0.41265785 | F28: 0.4127 | G28: 4 | H28: =IF(ROUND(E28,G28)=ROUND(F28,G28),"OK","DIVERGE") -> OK
B29: % fechado — Q3-2025 (fim da zona "queda atípica") | C29: idem — zona sombreada do gráfico | D29: =_xlfn.FORMULATEXT(E29) -> ='Q1 - Summary'!G17 | E29: ='Q1 - Summary'!G17 -> 0.20229743 | F29: 0.2023 | G29: 4 | H29: =IF(ROUND(E29,G29)=ROUND(F29,G29),"OK","DIVERGE") -> OK
B30: % fechado — Q4-2025 (último trimestre) | C30: idem — gráfico de linha | D30: =_xlfn.FORMULATEXT(E30) -> ='Q1 - Summary'!H17 | E30: ='Q1 - Summary'!H17 -> 0.21435094 | F30: 0.2144 | G30: 4 | H30: =IF(ROUND(E30,G30)=ROUND(F30,G30),"OK","DIVERGE") -> OK
B32: ="Conferência: "&COUNTIF(H7:H30,"OK")&" de "&COUNTA(H7:H30)&" métricas batem com o dashboard, ponto a ponto." -> Conferência: 24 de 24 métricas batem com o dashboard, ponto a ponto.

Sheet Lookup_PropertyType
A1: raw (qualquer grafia) | B1: normalizado | D1: Nota: VLOOKUP de texto no Excel nao diferencia maiuscula/minuscula, entao 'Apartment'/'APARTMENT' ja casam com 'apartment' automaticamente.
A2: apartment | B2: apartment
A3: apto | B3: apartment
A4: apartamento | B4: apartment
A5: house | B5: house
A6: casa | B6: house
A7: commercial | B7: other
A8: land | B8: other

Sheet DataBase
A1: id | B1: credit_approval | C1: closed_at | D1: state | E1: monthly_income | F1: loan_term | G1: credit_score | H1: property_value | I1: loan_amount | J1: property_type | K1: customer_age | L1: reason | M1: channel | N1: profession_type | O1: property_type_norm | P1: is_closed_valid
A2: 1 | B2: 45309 | D2: SP | E2: 7000 | H2: 700000 | I2: 120000 | J2: apartment | K2: 47 | L2: debts_refinancing | M2: offline | N2: businessman | O2: =IF(TRIM(J2)="","NULL",IFERROR(VLOOKUP(TRIM(J2),Lookup_PropertyType!$A:$B,2,FALSE()),"other")) -> apartment | P2: =IF(AND(C2<>"",C2>=B2),1,0) -> 0
A3: 2 | B3: 45523 | C3: 45565 | D3: SP | E3: 7753 | H3: 1500000 | I3: 140000 | J3: house | K3: 45 | L3: debts_payment | M3: organic | N3: freelancer | O3: =IF(TRIM(J3)="","NULL",IFERROR(VLOOKUP(TRIM(J3),Lookup_PropertyType!$A:$B,2,FALSE()),"other")) -> house | P3: =IF(AND(C3<>"",C3>=B3),1,0) -> 1
A4: 3 | B4: 45501 | D4: SP | E4: 30000 | H4: 200000 | I4: 108000 | J4: apartment | K4: 44 | L4: investment_in_own_business | M4: organic | N4: clt | O4: =IF(TRIM(J4)="","NULL",IFERROR(VLOOKUP(TRIM(J4),Lookup_PropertyType!$A:$B,2,FALSE()),"other")) -> apartment | P4: =IF(AND(C4<>"",C4>=B4),1,0) -> 0
A5: 4 | B5: 45576 | D5: SP | E5: 20000 | H5: 800000 | I5: 150000 | J5: apartment | K5: 58 | L5: debts_payment | M5: organic | N5: businessman | O5: =IF(TRIM(J5)="","NULL",IFERROR(VLOOKUP(TRIM(J5),Lookup_PropertyType!$A:$B,2,FALSE()),"other")) -> apartment | P5: =IF(AND(C5<>"",C5>=B5),1,0) -> 0
A6: 5 | B6: 45858 | C6: 45915 | D6: SP | E6: 9000 | H6: 600000 | I6: 140000 | J6: house | K6: 57 | L6: investment_in_own_business | M6: offline | N6: businessman | O6: =IF(TRIM(J6)="","NULL",IFERROR(VLOOKUP(TRIM(J6),Lookup_PropertyType!$A:$B,2,FALSE()),"other")) -> house | P6: =IF(AND(C6<>"",C6>=B6),1,0) -> 1
A7: 6 | B7: 45174.5 | C7: 45558 | D7: SP | E7: 9500 | H7: 250000 | I7: 100000 | J7: house | K7: 58 | L7: debts_payment | M7: organic | N7: retired | O7: =IF(TRIM(J7)="","NULL",IFERROR(VLOOKUP(TRIM(J7),Lookup_PropertyType!$A:$B,2,FALSE()),"other")) -> house | P7: =IF(AND(C7<>"",C7>=B7),1,0) -> 1
A8: 7 | B8: 45506 | D8: MG | E8: 7500 | H8: 280000 | I8: 120000 | J8: apartment | K8: 39 | L8: investment_in_own_business | M8: organic | N8: clt | O8: =IF(TRIM(J8)="","NULL",IFERROR(VLOOKUP(TRIM(J8),Lookup_PropertyType!$A:$B,2,FALSE()),"other")) -> apartment | P8: =IF(AND(C8<>"",C8>=B8),1,0) -> 0
A9: 8 | B9: 45526 | D9: SP | E9: 15000 | H9: 280000 | I9: 80000 | J9: apartment | K9: 59 | L9: others | M9: organic | N9: businessman | O9: =IF(TRIM(J9)="","NULL",IFERROR(VLOOKUP(TRIM(J9),Lookup_PropertyType!$A:$B,2,FALSE()),"other")) -> apartment | P9: =IF(AND(C9<>"",C9>=B9),1,0) -> 0
A10: 9 | B10: 45535 | C10: 45565 | D10: SC | E10: 3000 | H10: 250000 | I10: 50000 | J10: house | K10: 57 | L10: debts_payment | M10: organic | N10: retired | O10: =IF(TRIM(J10)="","NULL",IFERROR(VLOOKUP(TRIM(J10),Lookup_PropertyType!$A:$B,2,FALSE()),"other")) -> house | P10: =IF(AND(C10<>"",C10>=B10),1,0) -> 1
A11: 10 | B11: 45520 | D11: SP | E11: 25000 | H11: 900000 | I11: 400000 | J11: Commercial | K11: 60 | L11: debts_payment | M11: organic | N11: businessman | O11: =IF(TRIM(J11)="","NULL",IFERROR(VLOOKUP(TRIM(J11),Lookup_PropertyType!$A:$B,2,FALSE()),"other")) -> other | P11: =IF(AND(C11<>"",C11>=B11),1,0) -> 0
A12: 11 | B12: 45551 | C12: 45596 | D12: SP | E12: 7000 | H12: 270000 | I12: 130000 | J12: apartment | K12: 45 | L12: debts_payment | M12: organic | N12: businessman | O12: =IF(TRIM(J12)="","NULL",IFERROR(VLOOKUP(TRIM(J12),Lookup_PropertyType!$A:$B,2,FALSE()),"other")) -> apartment | P12: =IF(AND(C12<>"",C12>=B12),1,0) -> 1
A13: 12 | B13: 45509 | D13: SP | E13: 3000 | H13: 250000 | I13: 50000 | J13: house | K13: 26 | L13: investment_in_own_business | M13: organic | N13: businessman | O13: =IF(TRIM(J13)="","NULL",IFERROR(VLOOKUP(TRIM(J13),Lookup_PropertyType!$A:$B,2,FALSE()),"other")) -> house | P13: =IF(AND(C13<>"",C13>=B13),1,0) -> 0
A14: 13 | B14: 45491 | C14: 45474 | D14: SP | E14: 10800 | H14: 250000 | I14: 130000 | J14: apartment | K14: 39 | L14: debts_payment | M14: organic | N14: clt | O14: =IF(TRIM(J14)="","NULL",IFERROR(VLOOKUP(TRIM(J14),Lookup_PropertyType!$A:$B,2,FALSE()),"other")) -> apartment | P14: =IF(AND(C14<>"",C14>=B14),1,0) -> 0
A15: 14 | B15: 45506 | C15: 45547 | D15: SP | E15: 10000 | H15: 700000 | I15: 64000 | J15: house | K15: 53 | L15: debts_payment | M15: other | N15: clt | O15: =IF(TRIM(J15)="","NULL",IFERROR(VLOOKUP(TRIM(J15),Lookup_PropertyType!$A:$B,2,FALSE()),"other")) -> house | P15: =IF(AND(C15<>"",C15>=B15),1,0) -> 1
A16: 15 | B16: 45649 | D16: SP | E16: 25000 | H16: 700000 | I16: 200000 | J16: house | K16: 53 | L16: investment_in_own_business | M16: organic | N16: freelancer | O16: =IF(TRIM(J16)="","NULL",IFERROR(VLOOKUP(TRIM(J16),Lookup_PropertyType!$A:$B,2,FALSE()),"other")) -> house | P16: =IF(AND(C16<>"",C16>=B16),1,0) -> 0
A17: 16 | B17: 45537 | D17: PR | E17: 42000 | H17: 470000 | I17: 150000 | J17: apartment | K17: 46 | L17: debts_payment | M17: organic | N17: businessman | O17: =IF(TRIM(J17)="","NULL",IFERROR(VLOOKUP(TRIM(J17),Lookup_PropertyType!$A:$B,2,FALSE()),"other")) -> apartment | P17: =IF(AND(C17<>"",C17>=B17),1,0) -> 0
A18: 17 | B18: 45565 | C18: 45529 | D18: SP | E18: 6000 | H18: 300000 | I18: 50000 | J18: house | K18: 60 | L18: debts_payment | M18: organic | N18: public_employee | O18: =IF(TRIM(J18)="","NULL",IFERROR(VLOOKUP(TRIM(J18),Lookup_PropertyType!$A:$B,2,FALSE()),"other")) -> house | P18: =IF(AND(C18<>"",C18>=B18),1,0) -> 0
A19: 18 | B19: 45516 | C19: 45599 | D19: SP | E19: 28000 | H19: 600000 | I19: 230000 | J19: apartment | K19: 55 | L19: debts_payment | M19: organic | N19: clt | O19: =IF(TRIM(J19)="","NULL",IFERROR(VLOOKUP(TRIM(J19),Lookup_PropertyType!$A:$B,2,FALSE()),"other")) -> apartment | P19: =IF(AND(C19<>"",C19>=B19),1,0) -> 1
A20: 19 | B20: 45544 | C20: 45584 | D20: SP | E20: 8500 | H20: 600000 | I20: 50000 | J20: apartment | K20: 43 | M20: offline | N20: clt | O20: =IF(TRIM(J20)="","NULL",IFERROR(VLOOKUP(TRIM(J20),Lookup_PropertyType!$A:$B,2,FALSE()),"other")) -> apartment | P20: =IF(AND(C20<>"",C20>=B20),1,0) -> 1
A21: 20 | B21: 45530 | C21: 45585 | D21: SP | E21: 9000 | H21: 450000 | I21: 150000 | K21: 55 | L21: debts_payment | M21: organic | N21: self_employed | O21: =IF(TRIM(J21)="","NULL",IFERROR(VLOOKUP(TRIM(J21),Lookup_PropertyType!$A:$B,2,FALSE()),"other")) -> NULL | P21: =IF(AND(C21<>"",C21>=B21),1,0) -> 1
A22: 21 | B22: 45507 | C22: 45582 | D22: PR | E22: 20000 | H22: 650000 | I22: 350000 | J22: house | K22: 44 | L22: debts_refinancing | M22: organic | N22: businessman | O22: =IF(TRIM(J22)="","NULL",IFERROR(VLOOKUP(TRIM(J22),Lookup_PropertyType!$A:$B,2,FALSE()),"other")) -> house | P22: =IF(AND(C22<>"",C22>=B22),1,0) -> 1
A23: 22 | B23: 45558 | C23: 45610 | D23: CE | E23: 50000 | H23: 1300000 | I23: 700000 | J23: apartment | K23: 49 | L23: debts_refinancing | M23: other | N23: public_employee | O23: =IF(TRIM(J23)="","NULL",IFERROR(VLOOKUP(TRIM(J23),Lookup_PropertyType!$A:$B,2,FALSE()),"other")) -> apartment | P23: =IF(AND(C23<>"",C23>=B23),1,0) -> 1
A24: 23 | B24: 45523 | C24: 45596 | D24: SP | E24: 5000 | H24: 500000 | I24: 40000 | J24: apartment | K24: 56 | L24: debts_refinancing | M24: organic | N24: businessman | O24: =IF(TRIM(J24)="","NULL",IFERROR(VLOOKUP(TRIM(J24),Lookup_PropertyType!$A:$B,2,FALSE()),"other")) -> apartment | P24: =IF(AND(C24<>"",C24>=B24),1,0) -> 1
A25: 24 | B25: 45583 | C25: 45647 | D25: SP | E25: 50000 | H25: 800000 | I25: 400000 | J25: house | K25: 48 | L25: debts_payment | M25: organic | N25: businessman | O25: =IF(TRIM(J25)="","NULL",IFERROR(VLOOKUP(TRIM(J25),Lookup_PropertyType!$A:$B,2,FALSE()),"other")) -> house | P25: =IF(AND(C25<>"",C25>=B25),1,0) -> 1
A26: 25 | B26: 45516 | D26: SP | E26: 12000 | H26: 500000 | I26: 150000 | J26: house | K26: 51 | L26: debts_payment | M26: other | N26: public_employee | O26: =IF(TRIM(J26)="","NULL",IFERROR(VLOOKUP(TRIM(J26),Lookup_PropertyType!$A:$B,2,FALSE()),"other")) -> house | P26: =IF(AND(C26<>"",C26>=B26),1,0) -> 0
A27: 26 | B27: 45521 | C27: 45575 | D27: SP | E27: 17000 | H27: 800000 | I27: 175000 | J27: apartment | K27: 51 | L27: debts_payment | M27: organic | N27: clt | O27: =IF(TRIM(J27)="","NULL",IFERROR(VLOOKUP(TRIM(J27),Lookup_PropertyType!$A:$B,2,FALSE()),"other")) -> apartment | P27: =IF(AND(C27<>"",C27>=B27),1,0) -> 1
A28: 27 | B28: 45521 | C28: 45655 | D28: MG | E28: 16000 | H28: 400000 | I28: 70000 | J28: apartment | K28: 48 | L28: debts_payment | M28: organic | N28: clt | O28: =IF(TRIM(J28)="","NULL",IFERROR(VLOOKUP(TRIM(J28),Lookup_PropertyType!$A:$B,2,FALSE()),"other")) -> apartment | P28: =IF(AND(C28<>"",C28>=B28),1,0) -> 1
A29: 28 | B29: 45547 | D29: SP | E29: 12000 | H29: 350000 | I29: 100000 | J29: commercial | K29: 62 | L29: others | M29: organic | N29: businessman | O29: =IF(TRIM(J29)="","NULL",IFERROR(VLOOKUP(TRIM(J29),Lookup_PropertyType!$A:$B,2,FALSE()),"other")) -> other | P29: =IF(AND(C29<>"",C29>=B29),1,0) -> 0
A30: 29 | B30: 45536 | D30: SP | E30: 5708 | H30: 400000 | I30: 60000 | J30: house | K30: 49 | L30: debts_payment | M30: organic | N30: clt | O30: =IF(TRIM(J30)="","NULL",IFERROR(VLOOKUP(TRIM(J30),Lookup_PropertyType!$A:$B,2,FALSE()),"other")) -> house | P30: =IF(AND(C30<>"",C30>=B30),1,0) -> 0
A31: 30 | B31: 45527.96 | D31: SP | E31: 6500 | H31: 230000 | I31: 110000 | J31: apartment | K31: 46 | L31: debts_payment | M31: organic | N31: businessman | O31: =IF(TRIM(J31)="","NULL",IFERROR(VLOOKUP(TRIM(J31),Lookup_PropertyType!$A:$B,2,FALSE()),"other")) -> apartment | P31: =IF(AND(C31<>"",C31>=B31),1,0) -> 0
A32: 31 | B32: 45551 | C32: 45612 | D32: SP | E32: 60000 | H32: 550000 | I32: 200000 | J32: commercial | K32: 50 | L32: debts_payment | M32: offline | N32: businessman | O32: =IF(TRIM(J32)="","NULL",IFERROR(VLOOKUP(TRIM(J32),Lookup_PropertyType!$A:$B,2,FALSE()),"other")) -> other | P32: =IF(AND(C32<>"",C32>=B32),1,0) -> 1
A33: 32 | B33: 45547 | D33: MG | E33: 12000 | H33: 1300000 | I33: 140000 | J33: apartment | K33: 57 | L33: investment_in_own_business | M33: social_media | N33: businessman | O33: =IF(TRIM(J33)="","NULL",IFERROR(VLOOKUP(TRIM(J33),Lookup_PropertyType!$A:$B,2,FALSE()),"other")) -> apartment | P33: =IF(AND(C33<>"",C33>=B33),1,0) -> 0
A34: 33 | B34: 45528 | C34: 45536 | D34: SP | E34: 16000 | H34: 1090000 | I34: 200000 | J34: apartment | K34: 53 | L34: investment_in_own_business | M34: organic | N34: businessman | O34: =IF(TRIM(J34)="","NULL",IFERROR(VLOOKUP(TRIM(J34),Lookup_PropertyType!$A:$B,2,FALSE()),"other")) -> apartment | P34: =IF(AND(C34<>"",C34>=B34),1,0) -> 1
A35: 34 | B35: 45536 | C35: 45572 | D35: SP | E35: 14000 | H35: 750000 | I35: 100000 | J35: apartment | K35: 43 | L35: debts_refinancing | M35: organic | N35: clt | O35: =IF(TRIM(J35)="","NULL",IFERROR(VLOOKUP(TRIM(J35),Lookup_PropertyType!$A:$B,2,FALSE()),"other")) -> apartment | P35: =IF(AND(C35<>"",C35>=B35),1,0) -> 1
A36: 35 | B36: 45724 | C36: 45766 | D36: RS | E36: 32000 | H36: 800000 | I36: 350000 | J36: house | K36: 57 | L36: debts_payment | M36: organic | N36: retired | O36: =IF(TRIM(J36)="","NULL",IFERROR(VLOOKUP(TRIM(J36),Lookup_PropertyType!$A:$B,2,FALSE()),"other")) -> house | P36: =IF(AND(C36<>"",C36>=B36),1,0) -> 1
A37: 36 | B37: 45864 | C37: 45904 | D37: SP | E37: 15000 | H37: 395000 | I37: 200000 | J37: apartment | K37: 48 | L37: others | M37: organic | N37: businessman | O37: =IF(TRIM(J37)="","NULL",IFERROR(VLOOKUP(TRIM(J37),Lookup_PropertyType!$A:$B,2,FALSE()),"other")) -> apartment | P37: =IF(AND(C37<>"",C37>=B37),1,0) -> 1
A38: 37 | B38: 45562 | D38: SP | E38: 7000 | H38: 450000 | I38: 130000 | J38: house | K38: 63 | L38: debts_payment | M38: organic | N38: freelancer | O38: =IF(TRIM(J38)="","NULL",IFERROR(VLOOKUP(TRIM(J38),Lookup_PropertyType!$A:$B,2,FALSE()),"other")) -> house | P38: =IF(AND(C38<>"",C38>=B38),1,0) -> 0
A39: 38 | B39: 45519 | C39: 45726 | D39: SP | E39: 65000 | H39: 700000 | I39: 120000 | K39: 40 | L39: debts_payment | M39: organic | N39: businessman | O39: =IF(TRIM(J39)="","NULL",IFERROR(VLOOKUP(TRIM(J39),Lookup_PropertyType!$A:$B,2,FALSE()),"other")) -> NULL | P39: =IF(AND(C39<>"",C39>=B39),1,0) -> 1
A40: 39 | B40: 45572 | C40: 45681 | D40: SP | E40: 5000 | H40: 250000 | I40: 30000 | J40: apartment | K40: 57 | L40: investment_in_own_business | M40: organic | N40: businessman | O40: =IF(TRIM(J40)="","NULL",IFERROR(VLOOKUP(TRIM(J40),Lookup_PropertyType!$A:$B,2,FALSE()),"other")) -> apartment | P40: =IF(AND(C40<>"",C40>=B40),1,0) -> 1
A41: 40 | B41: 45523 | C41: 45718 | D41: SP | E41: 6000 | H41: 300000 | I41: 30000 | J41: house | K41: 47 | L41: debts_payment | M41: other | N41: clt | O41: =IF(TRIM(J41)="","NULL",IFERROR(VLOOKUP(TRIM(J41),Lookup_PropertyType!$A:$B,2,FALSE()),"other")) -> house | P41: =IF(AND(C41<>"",C41>=B41),1,0) -> 1
A42: 41 | B42: 45534 | D42: SP | E42: 19750 | H42: 350000 | I42: 155000 | J42: apartment | K42: 49 | L42: debts_refinancing | M42: organic | N42: clt | O42: =IF(TRIM(J42)="","NULL",IFERROR(VLOOKUP(TRIM(J42),Lookup_PropertyType!$A:$B,2,FALSE()),"other")) -> apartment | P42: =IF(AND(C42<>"",C42>=B42),1,0) -> 0
A43: 42 | B43: 45729 | C43: 45827 | D43: MS | E43: 12000 | H43: 400000 | I43: 200000 | J43: apartment | K43: 38 | L43: debts_payment | M43: organic | N43: self_employed | O43: =IF(TRIM(J43)="","NULL",IFERROR(VLOOKUP(TRIM(J43),Lookup_PropertyType!$A:$B,2,FALSE()),"other")) -> apartment | P43: =IF(AND(C43<>"",C43>=B43),1,0) -> 1
A44: 43 | B44: 45859 | D44: MG | E44: 12752 | H44: 620000 | I44: 238000 | J44: house | K44: 61 | L44: debts_payment | M44: other | N44: retired | O44: =IF(TRIM(J44)="","NULL",IFERROR(VLOOKUP(TRIM(J44),Lookup_PropertyType!$A:$B,2,FALSE()),"other")) -> house | P44: =IF(AND(C44<>"",C44>=B44),1,0) -> 0
A45: 44 | B45: 45534 | C45: 45625 | D45: SP | E45: 5500 | H45: 280000 | I45: 100000 | J45: apartment | K45: 55 | L45: debts_payment | M45: organic | N45: businessman | O45: =IF(TRIM(J45)="","NULL",IFERROR(VLOOKUP(TRIM(J45),Lookup_PropertyType!$A:$B,2,FALSE()),"other")) -> apartment | P45: =IF(AND(C45<>"",C45>=B45),1,0) -> 1
A46: 45 | B46: 45555 | D46: PR | E46: 20000 | H46: 300000 | I46: 45000 | J46: apartment | K46: 36 | L46: debts_refinancing | M46: organic | N46: businessman | O46: =IF(TRIM(J46)="","NULL",IFERROR(VLOOKUP(TRIM(J46),Lookup_PropertyType!$A:$B,2,FALSE()),"other")) -> apartment | P46: =IF(AND(C46<>"",C46>=B46),1,0) -> 0
A47: 46 | B47: 45592 | D47: DF | E47: 26344 | H47: 800000 | I47: 120000 | J47: apartment | K47: 59 | L47: others | M47: offline | N47: clt | O47: =IF(TRIM(J47)="","NULL",IFERROR(VLOOKUP(TRIM(J47),Lookup_PropertyType!$A:$B,2,FALSE()),"other")) -> apartment | P47: =IF(AND(C47<>"",C47>=B47),1,0) -> 0
A48: 47 | B48: 45527 | C48: 45634 | D48: RJ | E48: 7900 | H48: 950000 | I48: 50000 | J48: apartment | K48: 68 | L48: debts_refinancing | M48: other | N48: retired | O48: =IF(TRIM(J48)="","NULL",IFERROR(VLOOKUP(TRIM(J48),Lookup_PropertyType!$A:$B,2,FALSE()),"other")) -> apartment | P48: =IF(AND(C48<>"",C48>=B48),1,0) -> 1
A49: 48 | B49: 45540 | D49: SP | E49: 13000 | H49: 500000 | I49: 200000 | J49: house | K49: 51 | L49: debts_refinancing | M49: organic | N49: public_employee | O49: =IF(TRIM(J49)="","NULL",IFERROR(VLOOKUP(TRIM(J49),Lookup_PropertyType!$A:$B,2,FALSE()),"other")) -> house | P49: =IF(AND(C49<>"",C49>=B49),1,0) -> 0
A50: 49 | B50: 45543 | C50: 45563 | D50: MG | E50: 7000 | H50: 450000 | I50: 120000 | J50: apartment | K50: 46 | L50: investment_in_own_business | M50: organic | N50: self_employed | O50: =IF(TRIM(J50)="","NULL",IFERROR(VLOOKUP(TRIM(J50),Lookup_PropertyType!$A:$B,2,FALSE()),"other")) -> apartment | P50: =IF(AND(C50<>"",C50>=B50),1,0) -> 1
A51: 50 | B51: 45557 | C51: 45648 | D51: RJ | E51: 46000 | H51: 1000000 | I51: 600000 | J51: house | K51: 47 | L51: real_estate_renovation | M51: organic | N51: clt | O51: =IF(TRIM(J51)="","NULL",IFERROR(VLOOKUP(TRIM(J51),Lookup_PropertyType!$A:$B,2,FALSE()),"other")) -> house | P51: =IF(AND(C51<>"",C51>=B51),1,0) -> 1
A52: 51 | B52: 45645 | D52: SP | E52: 50000 | H52: 1000000 | I52: 500000 | J52: land | K52: 54 | L52: others | M52: organic | N52: businessman | O52: =IF(TRIM(J52)="","NULL",IFERROR(VLOOKUP(TRIM(J52),Lookup_PropertyType!$A:$B,2,FALSE()),"other")) -> other | P52: =IF(AND(C52<>"",C52>=B52),1,0) -> 0
A53: 52 | B53: 45561 | C53: 45582 | D53: SP | E53: 8000 | H53: 350000 | I53: 140000 | J53: apartment | K53: 38 | L53: debts_payment | M53: other | N53: clt | O53: =IF(TRIM(J53)="","NULL",IFERROR(VLOOKUP(TRIM(J53),Lookup_PropertyType!$A:$B,2,FALSE()),"other")) -> apartment | P53: =IF(AND(C53<>"",C53>=B53),1,0) -> 1
A54: 53 | B54: 45681 | C54: 45708 | D54: SP | E54: 20000 | H54: 950000 | I54: 120000 | J54: apartment | K54: 45 | L54: debts_refinancing | M54: organic | N54: clt | O54: =IF(TRIM(J54)="","NULL",IFERROR(VLOOKUP(TRIM(J54),Lookup_PropertyType!$A:$B,2,FALSE()),"other")) -> apartment | P54: =IF(AND(C54<>"",C54>=B54),1,0) -> 1
A55: 54 | B55: 45585 | C55: 45614 | D55: SP | E55: 25000 | H55: 1000000 | I55: 300000 | J55: house | K55: 70 | L55: investment_in_own_business | M55: organic | N55: businessman | O55: =IF(TRIM(J55)="","NULL",IFERROR(VLOOKUP(TRIM(J55),Lookup_PropertyType!$A:$B,2,FALSE()),"other")) -> house | P55: =IF(AND(C55<>"",C55>=B55),1,0) -> 1
A56: 55 | B56: 45597 | D56: SP | E56: 15000 | H56: 600000 | I56: 50000 | J56: house | K56: 64 | L56: debts_payment | M56: organic | N56: businessman | O56: =IF(TRIM(J56)="","NULL",IFERROR(VLOOKUP(TRIM(J56),Lookup_PropertyType!$A:$B,2,FALSE()),"other")) -> house | P56: =IF(AND(C56<>"",C56>=B56),1,0) -> 0
A57: 56 | B57: 45548 | C57: 45558 | D57: ES | E57: 36000 | H57: 1600000 | I57: 400000 | J57: apartment | K57: 62 | L57: debts_payment | M57: organic | N57: clt | O57: =IF(TRIM(J57)="","NULL",IFERROR(VLOOKUP(TRIM(J57),Lookup_PropertyType!$A:$B,2,FALSE()),"other")) -> apartment | P57: =IF(AND(C57<>"",C57>=B57),1,0) -> 1
A58: 57 | B58: 45617 | C58: 45654 | D58: SP | E58: 12000 | H58: 600000 | I58: 200000 | J58: apartment | K58: 52 | L58: investment_in_own_business | M58: organic | N58: businessman | O58: =IF(TRIM(J58)="","NULL",IFERROR(VLOOKUP(TRIM(J58),Lookup_PropertyType!$A:$B,2,FALSE()),"other")) -> apartment | P58: =IF(AND(C58<>"",C58>=B58),1,0) -> 1
A59: 58 | B59: 45534 | D59: SP | E59: 15000 | H59: 450000 | I59: 150000 | J59: commercial | K59: 70 | L59: debts_payment | M59: organic | N59: self_employed | O59: =IF(TRIM(J59)="","NULL",IFERROR(VLOOKUP(TRIM(J59),Lookup_PropertyType!$A:$B,2,FALSE()),"other")) -> other | P59: =IF(AND(C59<>"",C59>=B59),1,0) -> 0
A60: 59 | B60: 45541 | C60: 45593 | D60: SP | E60: 5680 | H60: 500000 | I60: 106131 | J60: house | K60: 49 | L60: debts_refinancing | M60: other | N60: clt | O60: =IF(TRIM(J60)="","NULL",IFERROR(VLOOKUP(TRIM(J60),Lookup_PropertyType!$A:$B,2,FALSE()),"other")) -> house | P60: =IF(AND(C60<>"",C60>=B60),1,0) -> 1
A61: 60 | B61: 45206.5 | C61: 45592 | D61: SP | E61: 17000 | H61: 250000 | I61: 30000 | J61: house | K61: 51 | L61: others | M61: other | N61: clt | O61: =IF(TRIM(J61)="","NULL",IFERROR(VLOOKUP(TRIM(J61),Lookup_PropertyType!$A:$B,2,FALSE()),"other")) -> house | P61: =IF(AND(C61<>"",C61>=B61),1,0) -> 1
A62: 61 | B62: 45540 | C62: 45563 | D62: SP | E62: 30000 | H62: 900000 | I62: 150000 | J62: apto | K62: 53 | L62: debts_refinancing | M62: other | N62: clt | O62: =IF(TRIM(J62)="","NULL",IFERROR(VLOOKUP(TRIM(J62),Lookup_PropertyType!$A:$B,2,FALSE()),"other")) -> apartment | P62: =IF(AND(C62<>"",C62>=B62),1,0) -> 1
A63: 62 | B63: 45550 | C63: 45593 | D63: SP | E63: 35000 | H63: 1500000 | I63: 400000 | J63: house | K63: 49 | L63: debts_payment | M63: social_media | N63: businessman | O63: =IF(TRIM(J63)="","NULL",IFERROR(VLOOKUP(TRIM(J63),Lookup_PropertyType!$A:$B,2,FALSE()),"other")) -> house | P63: =IF(AND(C63<>"",C63>=B63),1,0) -> 1
A64: 63 | B64: 45579 | C64: 45626 | D64: SC | E64: 5000 | H64: 200000 | I64: 45000 | J64: apartment | K64: 54 | L64: real_estate_renovation | M64: organic | N64: clt | O64: =IF(TRIM(J64)="","NULL",IFERROR(VLOOKUP(TRIM(J64),Lookup_PropertyType!$A:$B,2,FALSE()),"other")) -> apartment | P64: =IF(AND(C64<>"",C64>=B64),1,0) -> 1
A65: 64 | B65: 45565 | C65: 45585 | D65: SP | E65: 50000 | H65: 2500000 | I65: 60000 | J65: house | K65: 57 | L65: investment_in_own_business | M65: organic | N65: businessman | O65: =IF(TRIM(J65)="","NULL",IFERROR(VLOOKUP(TRIM(J65),Lookup_PropertyType!$A:$B,2,FALSE()),"other")) -> house | P65: =IF(AND(C65<>"",C65>=B65),1,0) -> 1
A66: 65 | B66: 45570 | D66: SP | E66: 7000 | H66: 210000 | I66: 45000 | J66: house | K66: 47 | L66: debts_payment | M66: organic | N66: clt | O66: =IF(TRIM(J66)="","NULL",IFERROR(VLOOKUP(TRIM(J66),Lookup_PropertyType!$A:$B,2,FALSE()),"other")) -> house | P66: =IF(AND(C66<>"",C66>=B66),1,0) -> 0
A67: 66 | B67: 45540 | D67: MG | E67: 4500 | H67: 180000 | I67: 84000 | J67: apartment | K67: 39 | L67: investment_in_own_business | M67: offline | N67: clt | O67: =IF(TRIM(J67)="","NULL",IFERROR(VLOOKUP(TRIM(J67),Lookup_PropertyType!$A:$B,2,FALSE()),"other")) -> apartment | P67: =IF(AND(C67<>"",C67>=B67),1,0) -> 0
A68: 67 | B68: 45547 | D68: RJ | E68: 25000 | H68: 500000 | I68: 230000 | J68: house | K68: 39 | L68: debts_payment | M68: organic | N68: self_employed | O68: =IF(TRIM(J68)="","NULL",IFERROR(VLOOKUP(TRIM(J68),Lookup_PropertyType!$A:$B,2,FALSE()),"other")) -> house | P68: =IF(AND(C68<>"",C68>=B68),1,0) -> 0
A69: 68 | B69: 45540 | C69: 45554 | D69: MS | E69: 10000 | H69: 400000 | I69: 150000 | J69: house | K69: 50 | L69: debts_payment | M69: offline | N69: businessman | O69: =IF(TRIM(J69)="","NULL",IFERROR(VLOOKUP(TRIM(J69),Lookup_PropertyType!$A:$B,2,FALSE()),"other")) -> house | P69: =IF(AND(C69<>"",C69>=B69),1,0) -> 1
A70: 69 | B70: 45680 | D70: SP | E70: 6000 | H70: 400000 | I70: 30000 | J70: apartment | K70: 41 | L70: debts_payment | M70: other | N70: clt | O70: =IF(TRIM(J70)="","NULL",IFERROR(VLOOKUP(TRIM(J70),Lookup_PropertyType!$A:$B,2,FALSE()),"other")) -> apartment | P70: =IF(AND(C70<>"",C70>=B70),1,0) -> 0
A71: 70 | B71: 45652 | D71: TO | E71: 4700 | H71: 300000 | I71: 87000 | J71: house | K71: 65 | L71: investment_in_own_business | M71: offline | N71: public_employee | O71: =IF(TRIM(J71)="","NULL",IFERROR(VLOOKUP(TRIM(J71),Lookup_PropertyType!$A:$B,2,FALSE()),"other")) -> house | P71: =IF(AND(C71<>"",C71>=B71),1,0) -> 0
A72: 71 | B72: 45565 | C72: 45632 | D72: SP | E72: 9500 | H72: 400000 | I72: 90000 | J72: apartment | K72: 51 | L72: debts_payment | M72: organic | N72: clt | O72: =IF(TRIM(J72)="","NULL",IFERROR(VLOOKUP(TRIM(J72),Lookup_PropertyType!$A:$B,2,FALSE()),"other")) -> apartment | P72: =IF(AND(C72<>"",C72>=B72),1,0) -> 1
A73: 72 | B73: 45660 | C73: 45681 | D73: MS | E73: 15000 | H73: 1000000 | I73: 100000 | J73: house | K73: 58 | L73: debts_payment | M73: organic | N73: businessman | O73: =IF(TRIM(J73)="","NULL",IFERROR(VLOOKUP(TRIM(J73),Lookup_PropertyType!$A:$B,2,FALSE()),"other")) -> house | P73: =IF(AND(C73<>"",C73>=B73),1,0) -> 1
A74: 73 | B74: 45549 | C74: 45541 | D74: MG | E74: 15000 | H74: 650000 | I74: 280000 | J74: house | K74: 47 | L74: investment_in_own_business | M74: other | N74: businessman | O74: =IF(TRIM(J74)="","NULL",IFERROR(VLOOKUP(TRIM(J74),Lookup_PropertyType!$A:$B,2,FALSE()),"other")) -> house | P74: =IF(AND(C74<>"",C74>=B74),1,0) -> 0
A75: 74 | B75: 45674 | D75: SP | E75: 7000 | H75: 700000 | I75: 60000 | J75: house | K75: 58 | L75: debts_payment | M75: organic | N75: other | O75: =IF(TRIM(J75)="","NULL",IFERROR(VLOOKUP(TRIM(J75),Lookup_PropertyType!$A:$B,2,FALSE()),"other")) -> house | P75: =IF(AND(C75<>"",C75>=B75),1,0) -> 0
A76: 75 | B76: 45549 | C76: 45592 | D76: SP | E76: 41000 | H76: 370000 | I76: 180000 | J76: apartment | K76: 56 | L76: debts_payment | M76: organic | N76: clt | O76: =IF(TRIM(J76)="","NULL",IFERROR(VLOOKUP(TRIM(J76),Lookup_PropertyType!$A:$B,2,FALSE()),"other")) -> apartment | P76: =IF(AND(C76<>"",C76>=B76),1,0) -> 1
A77: 76 | B77: 45549 | C77: 45613 | D77: SP | E77: 12000 | H77: 350000 | I77: 100000 | J77: house | K77: 37 | L77: goods_acquisition | M77: organic | N77: clt | O77: =IF(TRIM(J77)="","NULL",IFERROR(VLOOKUP(TRIM(J77),Lookup_PropertyType!$A:$B,2,FALSE()),"other")) -> house | P77: =IF(AND(C77<>"",C77>=B77),1,0) -> 1
A78: 77 | B78: 45572 | D78: MS | E78: 30000 | H78: 650000 | I78: 400000 | J78: apartment | K78: 59 | L78: debts_payment | M78: organic | N78: freelancer | O78: =IF(TRIM(J78)="","NULL",IFERROR(VLOOKUP(TRIM(J78),Lookup_PropertyType!$A:$B,2,FALSE()),"other")) -> apartment | P78: =IF(AND(C78<>"",C78>=B78),1,0) -> 0
A79: 78 | B79: 45612 | C79: 45698 | D79: SP | E79: 15000 | H79: 1300000 | I79: 280000 | K79: 57 | L79: debts_refinancing | M79: organic | N79: businessman | O79: =IF(TRIM(J79)="","NULL",IFERROR(VLOOKUP(TRIM(J79),Lookup_PropertyType!$A:$B,2,FALSE()),"other")) -> NULL | P79: =IF(AND(C79<>"",C79>=B79),1,0) -> 1
A80: 79 | B80: 45946 | C80: 46004 | D80: SP | E80: 5320 | H80: 300000 | I80: 30000 | J80: apartment | K80: 37 | L80: debts_payment | M80: organic | N80: clt | O80: =IF(TRIM(J80)="","NULL",IFERROR(VLOOKUP(TRIM(J80),Lookup_PropertyType!$A:$B,2,FALSE()),"other")) -> apartment | P80: =IF(AND(C80<>"",C80>=B80),1,0) -> 1
A81: 80 | B81: 45565 | D81: CE | E81: 7000 | H81: 220000 | I81: 70000 | J81: apartment | K81: 65 | L81: debts_refinancing | M81: organic | N81: public_employee | O81: =IF(TRIM(J81)="","NULL",IFERROR(VLOOKUP(TRIM(J81),Lookup_PropertyType!$A:$B,2,FALSE()),"other")) -> apartment | P81: =IF(AND(C81<>"",C81>=B81),1,0) -> 0
A82: 81 | B82: 45549 | D82: SC | E82: 7300 | H82: 230000 | I82: 125000 | J82: apartment | K82: 38 | L82: debts_refinancing | M82: organic | N82: clt | O82: =IF(TRIM(J82)="","NULL",IFERROR(VLOOKUP(TRIM(J82),Lookup_PropertyType!$A:$B,2,FALSE()),"other")) -> apartment | P82: =IF(AND(C82<>"",C82>=B82),1,0) -> 0
A83: 82 | B83: 45590 | C83: 45624 | D83: SP | E83: 10000 | H83: 450000 | I83: 65000 | J83: apartment | K83: 42 | L83: debts_payment | M83: organic | N83: freelancer | O83: =IF(TRIM(J83)="","NULL",IFERROR(VLOOKUP(TRIM(J83),Lookup_PropertyType!$A:$B,2,FALSE()),"other")) -> apartment | P83: =IF(AND(C83<>"",C83>=B83),1,0) -> 1
A84: 83 | B84: 45583 | D84: SP | E84: 17000 | H84: 2200000 | I84: 160000 | J84: house | K84: 44 | L84: debts_payment | M84: organic | N84: self_employed | O84: =IF(TRIM(J84)="","NULL",IFERROR(VLOOKUP(TRIM(J84),Lookup_PropertyType!$A:$B,2,FALSE()),"other")) -> house | P84: =IF(AND(C84<>"",C84>=B84),1,0) -> 0
A85: 84 | B85: 45635 | C85: 45724 | D85: SP | E85: 8000 | H85: 190000 | I85: 60000 | J85: apartment | K85: 35 | L85: debts_payment | M85: other | N85: clt | O85: =IF(TRIM(J85)="","NULL",IFERROR(VLOOKUP(TRIM(J85),Lookup_PropertyType!$A:$B,2,FALSE()),"other")) -> apartment | P85: =IF(AND(C85<>"",C85>=B85),1,0) -> 1
A86: 85 | B86: 45708 | D86: PR | E86: 20000 | H86: 900000 | I86: 370000 | J86: apartment | K86: 46 | L86: debts_refinancing | M86: organic | N86: businessman | O86: =IF(TRIM(J86)="","NULL",IFERROR(VLOOKUP(TRIM(J86),Lookup_PropertyType!$A:$B,2,FALSE()),"other")) -> apartment | P86: =IF(AND(C86<>"",C86>=B86),1,0) -> 0
A87: 86 | B87: 45638 | D87: SP | E87: 3000 | H87: 320000 | I87: 359532 | J87: apartment | K87: 33 | L87: debts_payment | M87: organic | N87: businessman | O87: =IF(TRIM(J87)="","NULL",IFERROR(VLOOKUP(TRIM(J87),Lookup_PropertyType!$A:$B,2,FALSE()),"other")) -> apartment | P87: =IF(AND(C87<>"",C87>=B87),1,0) -> 0
A88: 87 | B88: 45564 | C88: 45527 | D88: SP | E88: 8000 | H88: 220000 | I88: 60000 | J88: apartment | K88: 55 | L88: others | M88: organic | N88: clt | O88: =IF(TRIM(J88)="","NULL",IFERROR(VLOOKUP(TRIM(J88),Lookup_PropertyType!$A:$B,2,FALSE()),"other")) -> apartment | P88: =IF(AND(C88<>"",C88>=B88),1,0) -> 0
A89: 88 | B89: 45927 | D89: CE | E89: 6000 | H89: 350000 | I89: 50000 | K89: 65 | L89: debts_payment | M89: other | N89: retired | O89: =IF(TRIM(J89)="","NULL",IFERROR(VLOOKUP(TRIM(J89),Lookup_PropertyType!$A:$B,2,FALSE()),"other")) -> NULL | P89: =IF(AND(C89<>"",C89>=B89),1,0) -> 0
A90: 89 | B90: 45579 | D90: SP | E90: 5400 | H90: 450000 | I90: 80000 | J90: house | K90: 67 | L90: real_estate_renovation | M90: organic | N90: self_employed | O90: =IF(TRIM(J90)="","NULL",IFERROR(VLOOKUP(TRIM(J90),Lookup_PropertyType!$A:$B,2,FALSE()),"other")) -> house | P90: =IF(AND(C90<>"",C90>=B90),1,0) -> 0
A91: 90 | B91: 45558 | C91: 45592 | D91: RS | E91: 7600 | H91: 200000 | I91: 80000 | J91: house | K91: 48 | L91: debts_payment | M91: organic | N91: clt | O91: =IF(TRIM(J91)="","NULL",IFERROR(VLOOKUP(TRIM(J91),Lookup_PropertyType!$A:$B,2,FALSE()),"other")) -> house | P91: =IF(AND(C91<>"",C91>=B91),1,0) -> 1
A92: 91 | B92: 45632 | D92: SP | E92: 5900 | H92: 300000 | I92: 100000 | J92: apartment | K92: 61 | L92: debts_payment | M92: organic | N92: retired | O92: =IF(TRIM(J92)="","NULL",IFERROR(VLOOKUP(TRIM(J92),Lookup_PropertyType!$A:$B,2,FALSE()),"other")) -> apartment | P92: =IF(AND(C92<>"",C92>=B92),1,0) -> 0
A93: 92 | B93: 45572 | C93: 45635 | D93: DF | E93: 30000 | H93: 240000 | I93: 120000 | J93: apartment | K93: 62 | L93: debts_payment | M93: organic | N93: clt | O93: =IF(TRIM(J93)="","NULL",IFERROR(VLOOKUP(TRIM(J93),Lookup_PropertyType!$A:$B,2,FALSE()),"other")) -> apartment | P93: =IF(AND(C93<>"",C93>=B93),1,0) -> 1
A94: 93 | B94: 45562 | D94: MG | E94: 38000 | H94: 280000 | I94: 140000 | J94: land | K94: 62 | L94: others | M94: organic | N94: businessman | O94: =IF(TRIM(J94)="","NULL",IFERROR(VLOOKUP(TRIM(J94),Lookup_PropertyType!$A:$B,2,FALSE()),"other")) -> other | P94: =IF(AND(C94<>"",C94>=B94),1,0) -> 0
A95: 94 | B95: 45666 | D95: SP | E95: 7000 | H95: 220000 | I95: 30000 | J95: apartment | K95: 38 | L95: debts_payment | M95: organic | N95: clt | O95: =IF(TRIM(J95)="","NULL",IFERROR(VLOOKUP(TRIM(J95),Lookup_PropertyType!$A:$B,2,FALSE()),"other")) -> apartment | P95: =IF(AND(C95<>"",C95>=B95),1,0) -> 0
A96: 95 | B96: 45579 | D96: SP | E96: 15000 | H96: 350000 | I96: 70000 | J96: apartment | K96: 62 | L96: debts_payment | M96: organic | N96: freelancer | O96: =IF(TRIM(J96)="","NULL",IFERROR(VLOOKUP(TRIM(J96),Lookup_PropertyType!$A:$B,2,FALSE()),"other")) -> apartment | P96: =IF(AND(C96<>"",C96>=B96),1,0) -> 0
A97: 96 | B97: 45596 | C97: 45654 | D97: SP | E97: 3921 | H97: 350000 | I97: 40000 | J97: house | K97: 39 | L97: real_estate_renovation | M97: offline | N97: clt | O97: =IF(TRIM(J97)="","NULL",IFERROR(VLOOKUP(TRIM(J97),Lookup_PropertyType!$A:$B,2,FALSE()),"other")) -> house | P97: =IF(AND(C97<>"",C97>=B97),1,0) -> 1
A98: 97 | B98: 45575 | D98: SP | E98: 22000 | H98: 250000 | I98: 100000 | J98: house | K98: 63 | L98: investment_in_own_business | M98: organic | N98: self_employed | O98: =IF(TRIM(J98)="","NULL",IFERROR(VLOOKUP(TRIM(J98),Lookup_PropertyType!$A:$B,2,FALSE()),"other")) -> house | P98: =IF(AND(C98<>"",C98>=B98),1,0) -> 0
A99: 98 | B99: 45593 | C99: 45620 | D99: DF | E99: 13000 | H99: 950000 | I99: 170000 | J99: apartment | K99: 50 | L99: debts_payment | M99: other | N99: public_employee | O99: =IF(TRIM(J99)="","NULL",IFERROR(VLOOKUP(TRIM(J99),Lookup_PropertyType!$A:$B,2,FALSE()),"other")) -> apartment | P99: =IF(AND(C99<>"",C99>=B99),1,0) -> 1
A100: 99 | B100: 45634 | D100: BA | E100: 80000 | H100: 800000 | I100: 300000 | J100: apartment | K100: 64 | L100: debts_payment | M100: organic | N100: public_employee | O100: =IF(TRIM(J100)="","NULL",IFERROR(VLOOKUP(TRIM(J100),Lookup_PropertyType!$A:$B,2,FALSE()),"other")) -> apartment | P100: =IF(AND(C100<>"",C100>=B100),1,0) -> 0
...

Sheet AI_Log
B2: AI Log (opcional)
B3: Se quiser, registre aqui os 2-5 prompts mais importantes que você usou e o que decidiu fazer com a resposta da IA (aceitar, ajustar, descartar). Não é obrigatório, mas conta como sinal positivo na avaliação.
B5: Questão | C5: Ferramenta | D5: Prompt enviado (resumo) | E5: Decisão a partir da resposta
B6: Q1/Q3/Q4 | C6: Claude (Cowork) | D6: Ler a aba DataBase sem nunca usar Read/cat direto no arquivo bruto; so perfilamento agregado (shape, dtypes, nunique, min/max) via script Python. | E6: Aceito - todo o projeto seguiu essa regra; nenhuma linha crua da base apareceu no chat.
B7: Geral | C7: Claude (Cowork) | D7: Perfilar profundamente a DataBase (nulos, duplicatas, datas invalidas, grafias de property_type, LTV>100%, idade invalida) so com contagens agregadas. | E7: Aceito e usado como base do Q4; numeros conferidos com formula viva no proprio Excel.
B8: Q1 | C8: Claude (Cowork) | D8: Preencher a aba Q1 - Summary com SUMIFS ao vivo (nao valor fixo), criando coluna auxiliar para normalizar property_type via VLOOKUP. | E8: Aceito, com ajuste: troquei formulas de array (AVERAGE/MEDIAN(IF(...))) por SUMPRODUCT/ArrayFormula explicito depois de validar no LibreOffice que o resultado batia com o script.
B9: Q2 | C9: Claude (Cowork) | D9: Calcular volume e conversao por canal e sugerir alocacao de investimento como Strategic Planner. | E9: Aceito o calculo; a recomendacao de alocacao foi revisada e sera defendida com raciocinio proprio na entrevista, nao e uma resposta 'de caixa preta' da IA.
B10: Todas | C10: Claude (Cowork) | D10: Validar cruzado: recalcular tudo em Python (kpis.json + testes automatizados) e comparar com os valores das formulas do Excel recalculadas no LibreOffice headless. | E10: Aceito - so segui para a entrega depois que os dois calculos bateram 100% (Q1, Q2 e Q3).
